openslide/__init__.py
openslide/_convert.cpython-37m-darwin.so
openslide/_version.py
openslide/deepzoom.py
openslide/lowlevel.py
openslide_wrapper-1.1.2.dist-info/LICENSE.txt
openslide_wrapper-1.1.2.dist-info/METADATA
openslide_wrapper-1.1.2.dist-info/WHEEL
openslide_wrapper-1.1.2.dist-info/top_level.txt
openslide_wrapper-1.1.2.dist-info/zip-safe
openslide_wrapper-1.1.2.dist-info/RECORD
